MANIFEST.in
setup.py
src/fsqio/__init__.py
src/fsqio.pants.buildgen.jvm.egg-info/PKG-INFO
src/fsqio.pants.buildgen.jvm.egg-info/SOURCES.txt
src/fsqio.pants.buildgen.jvm.egg-info/dependency_links.txt
src/fsqio.pants.buildgen.jvm.egg-info/namespace_packages.txt
src/fsqio.pants.buildgen.jvm.egg-info/requires.txt
src/fsqio.pants.buildgen.jvm.egg-info/top_level.txt
src/fsqio.pants.buildgen.jvm.egg-info/zip-safe
src/fsqio/pants/__init__.py
src/fsqio/pants/buildgen/__init__.py
src/fsqio/pants/buildgen/jvm/__init__.py
src/fsqio/pants/buildgen/jvm/register.py
src/fsqio/pants/buildgen/jvm/core/__init__.py
src/fsqio/pants/buildgen/jvm/core/map_java_exported_symbols.py
src/fsqio/pants/buildgen/jvm/core/map_jvm_symbol_to_source_tree.py
src/fsqio/pants/buildgen/jvm/core/map_third_party_jar_symbols.py
src/fsqio/pants/buildgen/jvm/scala/__init__.py
src/fsqio/pants/buildgen/jvm/scala/buildgen_scala.py
src/fsqio/pants/buildgen/jvm/scala/map_scala_library_used_addresses.py
src/fsqio/pants/buildgen/jvm/scala/scala_exported_symbols.py
src/fsqio/pants/buildgen/jvm/scala/scala_used_symbols.py
src/fsqio/pants/buildgen/jvm/scala/scalac_buildgen_task_mixin.py
src/fsqio/pants/buildgen/jvm/scala/third_party_map_jvm.py